CHANGES.txt
LICENSE.txt
MANIFEST.in
README.txt
setup.py
js/__init__.py
js.angularstrap.egg-info/PKG-INFO
js.angularstrap.egg-info/SOURCES.txt
js.angularstrap.egg-info/dependency_links.txt
js.angularstrap.egg-info/entry_points.txt
js.angularstrap.egg-info/namespace_packages.txt
js.angularstrap.egg-info/not-zip-safe
js.angularstrap.egg-info/requires.txt
js.angularstrap.egg-info/top_level.txt
js/angularstrap/__init__.py
js/angularstrap/test_angularstrap.txt
js/angularstrap/resources/angular-strap.js
js/angularstrap/resources/angular-strap.min.js
js/angularstrap/resources/angular-strap.min.js.map
js/angularstrap/resources/angular-strap.tpl.js
js/angularstrap/resources/angular-strap.tpl.min.js