Metadata-Version: 1.0
Name: js.angularstrap
Version: 2.1.6
Summary: Fanstatic packaging of AngularStrap
Home-page: UNKNOWN
Author: Fanstatic Developers
Author-email: fanstatic@googlegroups.com
License: BSD
Platform: UNKNOWN
